sphinxawesome/codelinter/__init__.py
sphinxawesome/codelinter/py.typed
sphinxawesome_codelinter-3.0.1.dist-info/METADATA
sphinxawesome_codelinter-3.0.1.dist-info/WHEEL
sphinxawesome_codelinter-3.0.1.dist-info/licenses/LICENSE
sphinxawesome_codelinter-3.0.1.dist-info/RECORD
