Metadata-Version: 2.4
Name: sphinxawesome-codelinter
Version: 3.0.1
Summary: A Sphinx extension to expose code blocks to external tools for linting
Project-URL: repository, https://github.com/kai687/sphinxawesome-codelinter
Project-URL: issues, https://github.com/kai687/sphinxawesome-codelinter/issues
Author-email: Kai Welke <kai687@pm.me>
License-File: LICENSE
Classifier: Framework :: Sphinx
Classifier: Framework :: Sphinx :: Extension
Classifier: License :: OSI Approved :: MIT License
Classifier: Programming Language :: Python
Classifier: Programming Language :: Python :: 3
Classifier: Programming Language :: Python :: 3.9
Classifier: Programming Language :: Python :: 3.10
Classifier: Programming Language :: Python :: 3.11
Classifier: Programming Language :: Python :: 3.12
Classifier: Programming Language :: Python :: 3.13
Classifier: Programming Language :: Python :: 3.14
Classifier: Topic :: Documentation
Classifier: Topic :: Documentation :: Sphinx
Classifier: Topic :: Software Development :: Documentation
Requires-Python: >=3.9
Requires-Dist: sphinx<10,>7
